btree.cpython-312-x86_64-linux-gnu.so
sortedcollections.cpython-312-x86_64-linux-gnu.so
sortedcollections_ext-0.1.1.dist-info/METADATA
sortedcollections_ext-0.1.1.dist-info/WHEEL
sortedcollections_ext-0.1.1.dist-info/top_level.txt
sortedcollections_ext-0.1.1.dist-info/RECORD
sortedcollections_ext-0.1.1.dist-info/licenses/LICENSE
