Metadata-Version: 2.4
Name: sortedcollections-ext
Version: 0.1.1
Summary: sortedcollections as a CPython extension module
Author: Alberto Azzari
License: GNU GENERAL PUBLIC LICENSE
Classifier: Programming Language :: Python :: 3
Classifier: Programming Language :: Python :: Implementation :: CPython
Classifier: License :: OSI Approved :: MIT License
Requires-Python: >=3.12
License-File: LICENSE
Provides-Extra: dev
Requires-Dist: pytest>=7; extra == "dev"
Requires-Dist: pytest-cov>=4; extra == "dev"
Requires-Dist: coverage>=7; extra == "dev"
Provides-Extra: bench
Requires-Dist: sortedcontainers>=2.4.0; extra == "bench"
Dynamic: license-file
